fscribe/__init__.py
fscribe/analyzer.py
fscribe/async_reader.py
fscribe/cli.py
fscribe/configuration.py
fscribe/core.py
fscribe/exceptions.py
fscribe/file_reader.py
fscribe/formatters.py
fscribe/generator.py
fscribe/interfaces.py
fscribe/main.py
fscribe/progress.py
fscribe/utils.py
fscribe/writer.py
fscribe-1.0.0.dist-info/licenses/LICENSE
fscribe-1.0.0.dist-info/METADATA
fscribe-1.0.0.dist-info/WHEEL
fscribe-1.0.0.dist-info/entry_points.txt
fscribe-1.0.0.dist-info/top_level.txt
fscribe-1.0.0.dist-info/RECORD
